pyee/__init__.py
pyee/asyncio.py
pyee/base.py
pyee/cls.py
pyee/executor.py
pyee/py.typed
pyee/trio.py
pyee/twisted.py
pyee/uplift.py
camera.ui_pyee-11.1.2.dist-info/LICENSE
camera.ui_pyee-11.1.2.dist-info/METADATA
camera.ui_pyee-11.1.2.dist-info/WHEEL
camera.ui_pyee-11.1.2.dist-info/top_level.txt
camera.ui_pyee-11.1.2.dist-info/RECORD
